{
  "title": "MSK Башни/монументы",
  "version": "1.0",
  "osmid": 2555133,
  "center": [ 55.7505412, 37.6174782 ],
  "zoom": 11,
  "layers": [
    {
      "title": "text",
      "markers": {
        "x1": [ 101, 55.747898, 37.497219 ],
        "x2": [ 102, 55.747898, 37.498329 ],
        "x3": [ 103, 55.747898, 37.499439 ],
        "x4": [ 104, 55.747898, 37.500549 ],
        "y1": [ 105, 55.747898, 37.501659 ],
        "y2": [ 106, 55.747898, 37.502769 ],
        "y3": [ 107, 55.747898, 37.503879 ],
        "y4": [ 108, 55.747898, 37.504989 ]
      }
    },
    {
      "title": "29.01.24 - 04.02.24",
      "markers": {
        "t1": [ 101, 55.747898, 37.497219 ],
        "m1": [ 105, 55.746546, 37.505155 ]
      }
    }
  ]
}
